lucidIo
