Metadata-Version: 2.1
Name: pyLucidIo
Version: 2.1.1
Summary: LucidControl USB IO Module Package
Home-page: http://www.lucid-control.com
Author: Klaus Ummenhofer
License: UNKNOWN
Platform: UNKNOWN
